passportmcp/__init__.py
passportmcp/cli.py
passportmcp/client.py
passportmcp/native_host.py
passportmcp/passportmcp.py
ppmcp-0.1.5.dist-info/METADATA
ppmcp-0.1.5.dist-info/WHEEL
ppmcp-0.1.5.dist-info/entry_points.txt
ppmcp-0.1.5.dist-info/RECORD
