Metadata-Version: 2.4
Name: ppmcp
Version: 0.1.5
Summary: Python SDK for Passport MCP
Author-email: Josh Mayer <josh@tollbit.com>
License: MIT
Keywords: automation,browser,mcp,passport
Requires-Python: >=3.10
Requires-Dist: httpx>=0.24.0
Requires-Dist: mcp>=0.1.0
Provides-Extra: dev
Requires-Dist: pytest; extra == 'dev'
